README.rst
setup.py
botodesu/__init__.py
botodesu/_version.py
botodesu/body.py
botodesu/dikuto.py
botodesu/exceptions.py
botodesu/methods.py
botodesu.egg-info/PKG-INFO
botodesu.egg-info/SOURCES.txt
botodesu.egg-info/dependency_links.txt
botodesu.egg-info/not-zip-safe
botodesu.egg-info/requires.txt
botodesu.egg-info/top_level.txt