Metadata-Version: 1.1
Name: botodesu
Version: 0.1
Summary: An automatically expanding Telegram bot API that supports the latest Telegram features.
Home-page: https://github.com/futursolo/botodesu
Author: Kaede Hoshikawa
Author-email: futursolo@icloud.com
License: MIT
Platform: UNKNOWN
Classifier: Operating System :: MacOS
Classifier: Operating System :: MacOS :: MacOS X
Classifier: Operating System :: Microsoft
Classifier: Operating System :: Microsoft :: Windows
Classifier: Operating System :: POSIX
Classifier: Operating System :: POSIX :: Linux
Classifier: Operating System :: Unix
Classifier: Programming Language :: Python
Classifier: Programming Language :: Python :: 3 :: Only
Classifier: Programming Language :: Python :: Implementation :: CPython
